beiker/__init__.py
beiker/app.py
beiker/beiker_string.py
beiker/data_cleaning.py
beiker/database.py
beiker/files.py
beiker/gui.py
beiker/image.py
beiker/iot.py
beiker/log.py
beiker/ocr.py
beiker/paddleocr.py
beiker/safe.py
beiker-0.0.8.dist-info/METADATA
beiker-0.0.8.dist-info/WHEEL
beiker-0.0.8.dist-info/top_level.txt
beiker-0.0.8.dist-info/RECORD
